AUTHORS
CHANGELOG.txt
DESCRIPTION
LICENSE
MANIFEST.in
README.rst
setup.cfg
setup.py
dated_values/__init__.py
dated_values/admin.py
dated_values/decorators.py
dated_values/forms.py
dated_values/models.py
dated_values/settings.py
dated_values/urls.py
dated_values/views.py
dated_values/migrations/0001_initial.py
dated_values/migrations/0002_auto__del_unique_datedvaluetype_ctype.py
dated_values/migrations/0003_auto__add_field_datedvaluetype_editable__add_field_datedvaluetype_hidd.py
dated_values/migrations/__init__.py
dated_values/static/dated_values/css/dated_values.css
dated_values/templates/dated_values/.empty
dated_values/templates/dated_values/values_management_form.html
dated_values/tests/__init__.py
dated_values/tests/factories.py
dated_values/tests/forms_tests.py
dated_values/tests/models_tests.py
dated_values/tests/runtests.py
dated_values/tests/south_settings.py
dated_values/tests/test_settings.py
dated_values/tests/urls.py
dated_values/tests/views_tests.py
dated_values/tests/test_app/__init__.py
dated_values/tests/test_app/models.py
dated_values/tests/test_app/templates/400.html
dated_values/tests/test_app/templates/500.html
dated_values/tests/test_app/templates/base.html
django_dated_values.egg-info/PKG-INFO
django_dated_values.egg-info/SOURCES.txt
django_dated_values.egg-info/dependency_links.txt
django_dated_values.egg-info/requires.txt
django_dated_values.egg-info/top_level.txt