Metadata-Version: 1.0
Name: django-dated-values
Version: 0.2
Summary: A reusable Django app that allows adding dated decimal values to any Django model
